{
    "data": {
        "name": "Downtown",
        "id": 1
    },
    "spaces": [
        {
            "type": 0,
            "pos": {
                "x": 0,
                "y": 0
            },
            "prev": -1,
            "next": 1
        },
        {
            "type": 0,
            "pos": {
                "x": 1,
                "y": 0
            },
            "prev": 0,
            "next": 2
        },
        {
            "type": 0,
            "pos": {
                "x": 2,
                "y": 0
            },
            "prev": 1,
            "next": 3
        },
        {
            "type": 0,
            "pos": {
                "x": 3,
                "y": 0
            },
            "prev": 2,
            "next": 4
        },
        {
            "type": 0,
            "pos": {
                "x": 4,
                "y": 0
            },
            "prev": 3,
            "next": 5
        },
        {
            "type": 0,
            "pos": {
                "x": 5,
                "y": 0
            },
            "prev": 4,
            "next": 6
        },
        {
            "type": 0,
            "pos": {
                "x": 6,
                "y": 0
            },
            "prev": 5,
            "next": 7
        },
        {
            "type": 0,
            "pos": {
                "x": 7,
                "y": 0
            },
            "prev": 6,
            "next": 8
        },
        {
            "type": 0,
            "pos": {
                "x": 8,
                "y": 0
            },
            "prev": 7,
            "next": 9
        },
        {
            "type": 0,
            "pos": {
                "x": 9,
                "y": 0
            },
            "prev": 8,
            "next": 10
        },
        {
            "type": 0,
            "pos": {
                "x": 0,
                "y": 1
            },
            "prev": 9,
            "next": 11
        },
        {
            "type": 0,
            "pos": {
                "x": 1,
                "y": 1
            },
            "prev": 10,
            "next": 12
        },
        {
            "type": 0,
            "pos": {
                "x": 2,
                "y": 1
            },
            "prev": 11,
            "next": 13
        },
        {
            "type": 0,
            "pos": {
                "x": 3,
                "y": 1
            },
            "prev": 12,
            "next": 14
        },
        {
            "type": 0,
            "pos": {
                "x": 4,
                "y": 1
            },
            "prev": 13,
            "next": 15
        },
        {
            "type": 0,
            "pos": {
                "x": 5,
                "y": 1
            },
            "prev": 14,
            "next": 16
        },
        {
            "type": 0,
            "pos": {
                "x": 6,
                "y": 1
            },
            "prev": 15,
            "next": 17
        },
        {
            "type": 0,
            "pos": {
                "x": 7,
                "y": 1
            },
            "prev": 16,
            "next": 18
        },
        {
            "type": 0,
            "pos": {
                "x": 8,
                "y": 1
            },
            "prev": 17,
            "next": 19
        },
        {
            "type": 0,
            "pos": {
                "x": 9,
                "y": 1
            },
            "prev": 18,
            "next": 20
        },
        {
            "type": 0,
            "pos": {
                "x": 0,
                "y": 2
            },
            "prev": 19,
            "next": 21
        },
        {
            "type": 0,
            "pos": {
                "x": 1,
                "y": 2
            },
            "prev": 20,
            "next": 22
        },
        {
            "type": 0,
            "pos": {
                "x": 2,
                "y": 2
            },
            "prev": 21,
            "next": 23
        },
        {
            "type": 0,
            "pos": {
                "x": 3,
                "y": 2
            },
            "prev": 22,
            "next": 24
        },
        {
            "type": 0,
            "pos": {
                "x": 4,
                "y": 2
            },
            "prev": 23,
            "next": 25
        },
        {
            "type": 0,
            "pos": {
                "x": 5,
                "y": 2
            },
            "prev": 24,
            "next": 26
        },
        {
            "type": 0,
            "pos": {
                "x": 6,
                "y": 2
            },
            "prev": 25,
            "next": 27
        },
        {
            "type": 0,
            "pos": {
                "x": 7,
                "y": 2
            },
            "prev": 26,
            "next": 28
        },
        {
            "type": 0,
            "pos": {
                "x": 8,
                "y": 2
            },
            "prev": 27,
            "next": 29
        },
        {
            "type": 0,
            "pos": {
                "x": 9,
                "y": 2
            },
            "prev": 28,
            "next": 30
        }
    ]
}